<?xml version="1.0" encoding="utf-8"?>
<key id="8243598a-d0cc-44f9-9aa1-a70571f04ccc" version="1">
  <creationDate>2024-09-03T01:28:09.4744096Z</creationDate>
  <activationDate>2024-09-03T01:28:09.4677932Z</activationDate>
  <expirationDate>2024-12-02T01:28:09.4677932Z</expirationDate>
  <descriptor deserializerType="Microsoft.AspNetCore.DataProtection.AuthenticatedEncryption.ConfigurationModel.AuthenticatedEncryptorDescriptorDeserializer, Microsoft.AspNetCore.DataProtection, Version=8.0.0.0, Culture=neutral, PublicKeyToken=adb9793829ddae60">
    <descriptor>
      <encryption algorithm="AES_256_CBC" />
      <validation algorithm="HMACSHA256" />
      <masterKey p4:requiresEncryption="true" xmlns:p4="http://schemas.asp.net/2015/03/dataProtection">
        <!-- Warning: the key below is in an unencrypted form. -->
        <value>ASnYKOVoPtgCpkLjLT/QPiQLeQsxImu3iRgeQ/c6yuzZlLZ8mAsovIw3Xb/l869ryqZkysu65uUZNCitu8illg==</value>
      </masterKey>
    </descriptor>
  </descriptor>
</key>